britishize/britishize.py
britishize-0.2.1.dist-info/WHEEL
britishize-0.2.1.dist-info/entry_points.txt
britishize-0.2.1.dist-info/METADATA
britishize-0.2.1.dist-info/RECORD
